turing_bot_client/TuringBotClient.py
turing_bot_client/__init__.py
turing_bot_client/example/.env
turing_bot_client/example/ExampleBot.py
TuringBotClient/__init__.py
turing_bot_client-0.0.4.post3.dist-info/WHEEL
turing_bot_client-0.0.4.post3.dist-info/METADATA
turing_bot_client-0.0.4.post3.dist-info/RECORD
