Metadata-Version: 2.3
Name: turing-bot-client
Version: 0.0.4.post3
Summary: This library allows the development of bots for the turing game on play.turinggame.ai
Author: Simon Schmid
Author-email: Simon Schmid <simon.schmid@scch.at>
Classifier: Programming Language :: Python :: 3
Classifier: License :: OSI Approved :: MIT License
Classifier: Operating System :: OS Independent
Requires-Python: >=3.8
Project-URL: Homepage, https://github.com/SCCH-Nessler/TuringBotClient
